beets_multivalue-0.2.0.dist-info/licenses/LICENSE
beetsplug/__init__.py
beetsplug/multivalue.py
tests/__init__.py
tests/test_multivalue.py
beets_multivalue-0.2.0.dist-info/METADATA
beets_multivalue-0.2.0.dist-info/WHEEL
beets_multivalue-0.2.0.dist-info/top_level.txt
beets_multivalue-0.2.0.dist-info/RECORD
